sumu/CandidateRestrictedScore.cp37-win_amd64.pyd
sumu/DAGR.cp37-win_amd64.pyd
sumu/__init__.py
sumu/_multivariate.py
sumu/aps.cp37-win_amd64.pyd
sumu/beeps.py
sumu/bnet.py
sumu/candidates.py
sumu/gadget.py
sumu/mcmc.py
sumu/mcmc_moves.py
sumu/scorer.cp37-win_amd64.pyd
sumu/weight_sum.cp37-win_amd64.pyd
sumu/zeta_transform.cp37-win_amd64.pyd
sumu/scores/__init__.py
sumu/scores/bge.py
sumu/utils/__init__.py
sumu/utils/bitmap.py
sumu/utils/io.py
sumu/utils/math_utils.py
sumu/utils/utils.py
sumu-0.1.2.dist-info/COPYING
sumu-0.1.2.dist-info/METADATA
sumu-0.1.2.dist-info/WHEEL
sumu-0.1.2.dist-info/top_level.txt
sumu-0.1.2.dist-info/RECORD
